htflow_utils-1.0.3.dist-info/METADATA
htflow_utils-1.0.3.dist-info/WHEEL
htflow_utils-1.0.3.dist-info/licenses/LICENSE
htflow_utils/__init__.py
htflow_utils/caching.py
htflow_utils/db_tools.py
htflow_utils/external_forces.py
htflow_utils/kpoints.py
htflow_utils/misc_tools.py
htflow_utils/optimade.py
htflow_utils/shaper.py
htflow_utils/vasp_tools.py
htflow_utils/workflows.py
htflow_utils-1.0.3.dist-info/RECORD
