Metadata-Version: 2.1
Name: htflow-utils
Version: 1.0.3
Summary: utility functions and classes for SurfFlow and TriboFlow
Author-Email: "Michael Wolloch, Firat Yalcin" <michael.wolloch@univie.ac.at, firat.yalcin@univie.ac.at>
License: MIT
Classifier: Development Status :: 3 - Alpha
Classifier: Intended Audience :: Science/Research
Classifier: Operating System :: OS Independent
Classifier: Programming Language :: Python :: 3
Classifier: Topic :: Other/Nonlisted Topic
Classifier: Topic :: Scientific/Engineering
Project-URL: Homepage, https://github.com/fyalcin/htflow-utils
Requires-Python: >=3.10
Requires-Dist: pymatgen
Requires-Dist: ase; extra == "workflows"
Requires-Dist: matgl; extra == "workflows"
Provides-Extra: workflows
